signalrgb/__init__.py
signalrgb/async_client.py
signalrgb/cli.py
signalrgb/client.py
signalrgb/constants.py
signalrgb/exceptions.py
signalrgb/model.py
signalrgb-1.0.1.dist-info/METADATA
signalrgb-1.0.1.dist-info/WHEEL
signalrgb-1.0.1.dist-info/entry_points.txt
signalrgb-1.0.1.dist-info/licenses/LICENSE
signalrgb-1.0.1.dist-info/RECORD
