Metadata-Version: 2.4
Name: signalrgb
Version: 1.0.1
Summary: A Python client for SignalRGB
Project-URL: Homepage, https://github.com/hyperb1iss/signalrgb-python
Project-URL: Issues, https://github.com/hyperb1iss/signalrgb-python/issues
Project-URL: Documentation, https://hyperb1iss.github.io/signalrgb-python/
Author-email: Stefanie Jane <stef@hyperbliss.tech>
License: Apache-2.0
License-File: LICENSE
Requires-Python: >=3.11
Requires-Dist: httpx>=0.27.0
Requires-Dist: mashumaro>=3.16
Requires-Dist: pre-commit>=4.2.0
Requires-Dist: requests>=2.32.4
Requires-Dist: rich>=14.0.0
Requires-Dist: ruff>=0.12.2
Requires-Dist: typer>=0.16.0
Requires-Dist: urllib3>=2.5.0
Requires-Dist: wcwidth>=0.2.13
